gmusicapi_scripts/__init__.py
gmusicapi_scripts/gmdelete.py
gmusicapi_scripts/gmdownload.py
gmusicapi_scripts/gmsearch.py
gmusicapi_scripts/gmsync.py
gmusicapi_scripts/gmupload.py
gmusicapi_scripts-0.5.0.dist-info/DESCRIPTION.rst
gmusicapi_scripts-0.5.0.dist-info/METADATA
gmusicapi_scripts-0.5.0.dist-info/RECORD
gmusicapi_scripts-0.5.0.dist-info/WHEEL
gmusicapi_scripts-0.5.0.dist-info/entry_points.txt
gmusicapi_scripts-0.5.0.dist-info/metadata.json
gmusicapi_scripts-0.5.0.dist-info/top_level.txt
