Metadata-Version: 2.0
Name: gmusicapi-scripts
Version: 0.5.0
Summary: A collection of scripts using gmusicapi-wrapper and gmusicapi.
Home-page: https://github.com/thebigmunch/gmusicapi-scripts
Author: thebigmunch
Author-email: mail@thebigmunch.me
License: MIT
Platform: UNKNOWN
Classifier: License :: OSI Approved :: MIT License
Classifier: Programming Language :: Python :: 3
Classifier: Programming Language :: Python :: 3.4
Classifier: Programming Language :: Python :: 3.5
Requires-Dist: docopt-unicode
Requires-Dist: gmusicapi-wrapper (>=0.5.0)
